{
  "_meta": {
    "generadoEn": "2026-06-16T10:20:37.940Z",
    "generadoPor": "github-actions · scripts/generar-snapshots.js",
    "fuente": "calculado desde stocks-actual + movimientos-2026",
    "fechaCierre": "2026-06-15",
    "formula": "total_actual_snapshot − movimientos_netos_de_hoy"
  },
  "ok": true,
  "fechaCierre": "2026-06-15",
  "totales_por_tipo": {
    "CLIENTES": {
      "total_pallets": 194775
    },
    "RETAIL": {
      "total_pallets": 552327
    }
  },
  "detalle": {
    "total_actual_snapshot": {
      "CLIENTES": 195009,
      "RETAIL": 552885
    },
    "neto_movimientos_hoy": {
      "CLIENTES": 234,
      "RETAIL": 558
    },
    "fecha_calculo": "2026-06-16"
  }
}